valyutauzb/__init__.py
valyutauzb-0.0.1.dist-info/METADATA
valyutauzb-0.0.1.dist-info/WHEEL
valyutauzb-0.0.1.dist-info/top_level.txt
valyutauzb-0.0.1.dist-info/RECORD
