Metadata-Version: 2.1
Name: valyutauzb
Version: 0.0.1
Summary: Ushbu kutubxona valyutani bilish uchun ishlatiladi
Author: Hikmatullayev Islombek
Author-email: gimlerpro8899@gmail.com
